PurityThresholdPruning/PurityThresholdPruning.py
PurityThresholdPruning/__init__.py
purity_threshold_pruning-0.1.0.dist-info/licenses/LICENSE
purity_threshold_pruning-0.1.0.dist-info/METADATA
purity_threshold_pruning-0.1.0.dist-info/WHEEL
purity_threshold_pruning-0.1.0.dist-info/top_level.txt
purity_threshold_pruning-0.1.0.dist-info/RECORD
