Metadata-Version: 2.4
Name: Purity-Threshold-Pruning
Version: 0.1.0
Summary: A pruning algorithm for the scikit-learn RandomForestClassifier which minimizes model complexity while considering a user-specified tolerance for accuracy loss.
Home-page: https://github.com/Datou0718/Purity-Threshold-Pruning
Author: Yi-Chun Liao
Author-email: ycliao@gmail.com
License: MIT
Classifier: Programming Language :: Python :: 3
Classifier: License :: OSI Approved :: MIT License
Classifier: Operating System :: OS Independent
Requires-Python: >=3.6
License-File: LICENSE
Requires-Dist: numpy>=2.2.2
Requires-Dist: scikit-learn>=1.6.1
Dynamic: license-file
